{"name":"build-javascript","namedChunkGroups":{"polyfill":{"name":"polyfill","assets":[{"name":"webpack-runtime-70cffe8582ba8b71a65b.js","size":3335},{"name":"polyfill-8a4ac0b425b21e1d2155.js","size":85013}],"filteredAssets":0,"assetsSize":88348,"filteredAuxiliaryAssets":2,"auxiliaryAssetsSize":220017},"app":{"name":"app","assets":[{"name":"webpack-runtime-70cffe8582ba8b71a65b.js","size":3335},{"name":"framework-cb3fbf85335c3ab0f29c.js","size":141375},{"name":"styles.111c7bcf76e1e99550c3.css","size":30999},{"name":"app-f79e2e2a8956d23646e8.js","size":179787}],"filteredAssets":0,"assetsSize":355496,"filteredAuxiliaryAssets":8,"auxiliaryAssetsSize":1944258},"component---src-pages-index-jsx":{"name":"component---src-pages-index-jsx","assets":[{"name":"component---src-pages-index-jsx-73c231f9bccfe52259bb.js","size":150445}],"filteredAssets":0,"assetsSize":150445,"filteredAuxiliaryAssets":1,"auxiliaryAssetsSize":730209}},"assetsByChunkName":{"polyfill":["webpack-runtime-70cffe8582ba8b71a65b.js","polyfill-8a4ac0b425b21e1d2155.js"],"app":["webpack-runtime-70cffe8582ba8b71a65b.js","framework-cb3fbf85335c3ab0f29c.js","styles.111c7bcf76e1e99550c3.css","app-f79e2e2a8956d23646e8.js"],"component---src-pages-index-jsx":["component---src-pages-index-jsx-73c231f9bccfe52259bb.js"]},"childAssetsByChunkName":{}}